easy_push/__init__.py
easy_push-0.2.dist-info/DESCRIPTION.rst
easy_push-0.2.dist-info/METADATA
easy_push-0.2.dist-info/RECORD
easy_push-0.2.dist-info/WHEEL
easy_push-0.2.dist-info/metadata.json
easy_push-0.2.dist-info/top_level.txt
